Metadata-Version: 1.0
Name: pyclifactory
Version: 0.1
Summary: Prototype pyclifactory
Home-page: http://github.com/avattathil/pyclifactory
Author: Tony Vattathil
Author-email: avattathil@gmail.com
License: Apache 2.0
Platform: UNKNOWN
